sprintcore/__init__.py
sprintcore/main.py
sprintcore/cli/__init__.py
sprintcore/cli/doc_embeddings.py
sprintcore/cli/fix_bugs_agent.py
sprintcore/cli/prd2story.py
sprintcore/core/__init__.py
sprintcore/core/output_writer.py
sprintcore/core/parser.py
sprintcore/tests/test_output_writer.py
sprintcore/tests/test_parser.py
sprintcore-0.1.7.dist-info/licenses/LICENSE
sprintcore-0.1.7.dist-info/METADATA
sprintcore-0.1.7.dist-info/WHEEL
sprintcore-0.1.7.dist-info/entry_points.txt
sprintcore-0.1.7.dist-info/top_level.txt
sprintcore-0.1.7.dist-info/RECORD
