Metadata-Version: 2.4
Name: sprintcore
Version: 0.1.7
Summary: SprintCore CLI: Convert PRDs into structured sprints. Fix bugs based on bug report
Author-email: Spicewood Labs LLC <contact@sprintcore.ai>
License: MIT
Requires-Python: >=3.8
License-File: LICENSE
Requires-Dist: openai
Requires-Dist: python-dotenv
Requires-Dist: pyyaml
Requires-Dist: requests
Requires-Dist: langchain
Requires-Dist: langchain-openai
Requires-Dist: faiss-cpu
Requires-Dist: tqdm
Requires-Dist: PyYAML
Requires-Dist: rich
Requires-Dist: anthropic
Requires-Dist: tree-sitter==0.24.0
Requires-Dist: tree-sitter-javascript==0.23.1
Requires-Dist: tree-sitter-typescript==0.23.2
Requires-Dist: tiktoken==0.9.0
Requires-Dist: langchain-community
Dynamic: license-file
